{
  "history": {
    "AAPL": [
      {
        "t": 1777239428856,
        "p": 271.06
      },
      {
        "t": 1777241229247,
        "p": 271.06
      },
      {
        "t": 1777244267196,
        "p": 271.06
      },
      {
        "t": 1777247313680,
        "p": 271.06
      },
      {
        "t": 1777252629545,
        "p": 271.06
      },
      {
        "t": 1777265022494,
        "p": 271.06
      },
      {
        "t": 1777274845065,
        "p": 271.06
      },
      {
        "t": 1777282755290,
        "p": 271.06
      },
      {
        "t": 1777289228841,
        "p": 271.06
      },
      {
        "t": 1777295175428,
        "p": 271.06
      },
      {
        "t": 1777303065676,
        "p": 266.94
      },
      {
        "t": 1777309127199,
        "p": 266.38
      },
      {
        "t": 1777313539684,
        "p": 266.39
      },
      {
        "t": 1777319416160,
        "p": 267.7
      },
      {
        "t": 1777323662522,
        "p": 267.61
      }
    ],
    "MSFT": [
      {
        "t": 1777239428856,
        "p": 424.62
      },
      {
        "t": 1777241229247,
        "p": 424.62
      },
      {
        "t": 1777244267196,
        "p": 424.62
      },
      {
        "t": 1777247313680,
        "p": 424.62
      },
      {
        "t": 1777252629545,
        "p": 424.62
      },
      {
        "t": 1777265022494,
        "p": 424.62
      },
      {
        "t": 1777274845065,
        "p": 424.62
      },
      {
        "t": 1777282755290,
        "p": 424.62
      },
      {
        "t": 1777289228841,
        "p": 424.62
      },
      {
        "t": 1777295175428,
        "p": 424.62
      },
      {
        "t": 1777303065676,
        "p": 421.93
      },
      {
        "t": 1777309127199,
        "p": 424.04
      },
      {
        "t": 1777313539684,
        "p": 426.32
      },
      {
        "t": 1777319416160,
        "p": 425.59
      },
      {
        "t": 1777323662522,
        "p": 424.82
      }
    ],
    "GOOGL": [
      {
        "t": 1777239428856,
        "p": 344.4
      },
      {
        "t": 1777241229247,
        "p": 344.4
      },
      {
        "t": 1777244267196,
        "p": 344.4
      },
      {
        "t": 1777247313680,
        "p": 344.4
      },
      {
        "t": 1777252629545,
        "p": 344.4
      },
      {
        "t": 1777265022494,
        "p": 344.4
      },
      {
        "t": 1777274845065,
        "p": 344.4
      },
      {
        "t": 1777282755290,
        "p": 344.4
      },
      {
        "t": 1777289228841,
        "p": 344.4
      },
      {
        "t": 1777295175428,
        "p": 344.4
      },
      {
        "t": 1777303065676,
        "p": 351.31
      },
      {
        "t": 1777309127199,
        "p": 351.52
      },
      {
        "t": 1777313539684,
        "p": 353.04
      },
      {
        "t": 1777319416160,
        "p": 351.42
      },
      {
        "t": 1777323662522,
        "p": 350.34
      }
    ],
    "AMZN": [
      {
        "t": 1777239428856,
        "p": 263.99
      },
      {
        "t": 1777241229247,
        "p": 263.99
      },
      {
        "t": 1777244267196,
        "p": 263.99
      },
      {
        "t": 1777247313680,
        "p": 263.99
      },
      {
        "t": 1777252629545,
        "p": 263.99
      },
      {
        "t": 1777265022494,
        "p": 263.99
      },
      {
        "t": 1777274845065,
        "p": 263.99
      },
      {
        "t": 1777282755290,
        "p": 263.99
      },
      {
        "t": 1777289228841,
        "p": 263.99
      },
      {
        "t": 1777295175428,
        "p": 263.99
      },
      {
        "t": 1777303065676,
        "p": 261.57
      },
      {
        "t": 1777309127199,
        "p": 262.6
      },
      {
        "t": 1777313539684,
        "p": 261.88
      },
      {
        "t": 1777319416160,
        "p": 261.01
      },
      {
        "t": 1777323662522,
        "p": 261.12
      }
    ],
    "META": [
      {
        "t": 1777239428856,
        "p": 675.03
      },
      {
        "t": 1777241229247,
        "p": 675.03
      },
      {
        "t": 1777244267196,
        "p": 675.03
      },
      {
        "t": 1777247313680,
        "p": 675.03
      },
      {
        "t": 1777252629545,
        "p": 675.03
      },
      {
        "t": 1777265022494,
        "p": 675.03
      },
      {
        "t": 1777274845065,
        "p": 675.03
      },
      {
        "t": 1777282755290,
        "p": 675.03
      },
      {
        "t": 1777289228841,
        "p": 675.03
      },
      {
        "t": 1777295175428,
        "p": 675.03
      },
      {
        "t": 1777303065676,
        "p": 678.29
      },
      {
        "t": 1777309127199,
        "p": 677.42
      },
      {
        "t": 1777313539684,
        "p": 679.2
      },
      {
        "t": 1777319416160,
        "p": 679.1
      },
      {
        "t": 1777323662522,
        "p": 678.62
      }
    ],
    "NVDA": [
      {
        "t": 1777239428856,
        "p": 208.27
      },
      {
        "t": 1777241229247,
        "p": 208.27
      },
      {
        "t": 1777244267196,
        "p": 208.27
      },
      {
        "t": 1777247313680,
        "p": 208.27
      },
      {
        "t": 1777252629545,
        "p": 208.27
      },
      {
        "t": 1777265022494,
        "p": 208.27
      },
      {
        "t": 1777274845065,
        "p": 208.27
      },
      {
        "t": 1777282755290,
        "p": 208.27
      },
      {
        "t": 1777289228841,
        "p": 208.27
      },
      {
        "t": 1777295175428,
        "p": 208.27
      },
      {
        "t": 1777303065676,
        "p": 209.67
      },
      {
        "t": 1777309127199,
        "p": 212.58
      },
      {
        "t": 1777313539684,
        "p": 215.38
      },
      {
        "t": 1777319416160,
        "p": 216.36
      },
      {
        "t": 1777323662522,
        "p": 216.61
      }
    ],
    "TSLA": [
      {
        "t": 1777239428856,
        "p": 376.3
      },
      {
        "t": 1777241229247,
        "p": 376.3
      },
      {
        "t": 1777244267196,
        "p": 376.3
      },
      {
        "t": 1777247313680,
        "p": 376.3
      },
      {
        "t": 1777252629545,
        "p": 376.3
      },
      {
        "t": 1777265022494,
        "p": 376.3
      },
      {
        "t": 1777274845065,
        "p": 376.3
      },
      {
        "t": 1777282755290,
        "p": 376.3
      },
      {
        "t": 1777289228841,
        "p": 376.3
      },
      {
        "t": 1777295175428,
        "p": 376.3
      },
      {
        "t": 1777303065676,
        "p": 365.49
      },
      {
        "t": 1777309127199,
        "p": 373.67
      },
      {
        "t": 1777313539684,
        "p": 379.61
      },
      {
        "t": 1777319416160,
        "p": 379.43
      },
      {
        "t": 1777323662522,
        "p": 378.67
      }
    ],
    "AMD": [
      {
        "t": 1777239428856,
        "p": 347.81
      },
      {
        "t": 1777241229247,
        "p": 347.81
      },
      {
        "t": 1777244267196,
        "p": 347.81
      },
      {
        "t": 1777247313680,
        "p": 347.81
      },
      {
        "t": 1777252629545,
        "p": 347.81
      },
      {
        "t": 1777265022494,
        "p": 347.81
      },
      {
        "t": 1777274845065,
        "p": 347.81
      },
      {
        "t": 1777282755290,
        "p": 347.81
      },
      {
        "t": 1777289228841,
        "p": 347.81
      },
      {
        "t": 1777295175428,
        "p": 347.81
      },
      {
        "t": 1777303065676,
        "p": 335.32
      },
      {
        "t": 1777309127199,
        "p": 333.91
      },
      {
        "t": 1777313539684,
        "p": 335.5
      },
      {
        "t": 1777319416160,
        "p": 335.45
      },
      {
        "t": 1777323662522,
        "p": 334.63
      }
    ],
    "INTC": [
      {
        "t": 1777239428856,
        "p": 82.54
      },
      {
        "t": 1777241229247,
        "p": 82.54
      },
      {
        "t": 1777244267196,
        "p": 82.54
      },
      {
        "t": 1777247313680,
        "p": 82.54
      },
      {
        "t": 1777252629545,
        "p": 82.54
      },
      {
        "t": 1777265022494,
        "p": 82.54
      },
      {
        "t": 1777274845065,
        "p": 82.54
      },
      {
        "t": 1777282755290,
        "p": 82.54
      },
      {
        "t": 1777289228841,
        "p": 82.54
      },
      {
        "t": 1777295175428,
        "p": 82.54
      },
      {
        "t": 1777303065676,
        "p": 83.95
      },
      {
        "t": 1777309127199,
        "p": 83.86
      },
      {
        "t": 1777313539684,
        "p": 83.57
      },
      {
        "t": 1777319416160,
        "p": 84.29
      },
      {
        "t": 1777323662522,
        "p": 84.99
      }
    ],
    "NFLX": [
      {
        "t": 1777239428856,
        "p": 92.44
      },
      {
        "t": 1777241229247,
        "p": 92.44
      },
      {
        "t": 1777244267196,
        "p": 92.44
      },
      {
        "t": 1777247313680,
        "p": 92.44
      },
      {
        "t": 1777252629545,
        "p": 92.44
      },
      {
        "t": 1777265022494,
        "p": 92.44
      },
      {
        "t": 1777274845065,
        "p": 92.44
      },
      {
        "t": 1777282755290,
        "p": 92.44
      },
      {
        "t": 1777289228841,
        "p": 92.44
      },
      {
        "t": 1777295175428,
        "p": 92.44
      },
      {
        "t": 1777303065676,
        "p": 92.68
      },
      {
        "t": 1777309127199,
        "p": 92.17
      },
      {
        "t": 1777313539684,
        "p": 92.1
      },
      {
        "t": 1777319416160,
        "p": 91.56
      },
      {
        "t": 1777323662522,
        "p": 91.37
      }
    ],
    "HIMS": [
      {
        "t": 1777239428856,
        "p": 30.56
      },
      {
        "t": 1777241229247,
        "p": 30.56
      },
      {
        "t": 1777244267196,
        "p": 30.56
      },
      {
        "t": 1777247313680,
        "p": 30.56
      },
      {
        "t": 1777252629545,
        "p": 30.56
      },
      {
        "t": 1777265022494,
        "p": 30.56
      },
      {
        "t": 1777274845065,
        "p": 30.56
      },
      {
        "t": 1777282755290,
        "p": 30.56
      },
      {
        "t": 1777289228841,
        "p": 30.56
      },
      {
        "t": 1777295175428,
        "p": 30.56
      },
      {
        "t": 1777303065676,
        "p": 29.61
      },
      {
        "t": 1777309127199,
        "p": 29.31
      },
      {
        "t": 1777313539684,
        "p": 29.74
      },
      {
        "t": 1777319416160,
        "p": 29.3
      },
      {
        "t": 1777323662522,
        "p": 29.39
      }
    ],
    "HIMX": [
      {
        "t": 1777239428856,
        "p": 12.09
      },
      {
        "t": 1777241229247,
        "p": 12.09
      },
      {
        "t": 1777244267196,
        "p": 12.09
      },
      {
        "t": 1777247313680,
        "p": 12.09
      },
      {
        "t": 1777252629545,
        "p": 12.09
      },
      {
        "t": 1777265022494,
        "p": 12.09
      },
      {
        "t": 1777274845065,
        "p": 12.09
      },
      {
        "t": 1777282755290,
        "p": 12.09
      },
      {
        "t": 1777289228841,
        "p": 12.09
      },
      {
        "t": 1777295175428,
        "p": 12.09
      },
      {
        "t": 1777303065676,
        "p": 11.46
      },
      {
        "t": 1777309127199,
        "p": 11.28
      },
      {
        "t": 1777313539684,
        "p": 11.33
      },
      {
        "t": 1777319416160,
        "p": 11.46
      },
      {
        "t": 1777323662522,
        "p": 11.5
      }
    ],
    "NOW": [
      {
        "t": 1777239428856,
        "p": 90.17
      },
      {
        "t": 1777241229247,
        "p": 90.17
      },
      {
        "t": 1777244267196,
        "p": 90.17
      },
      {
        "t": 1777247313680,
        "p": 90.17
      },
      {
        "t": 1777252629545,
        "p": 90.17
      },
      {
        "t": 1777265022494,
        "p": 90.17
      },
      {
        "t": 1777274845065,
        "p": 90.17
      },
      {
        "t": 1777282755290,
        "p": 90.17
      },
      {
        "t": 1777289228841,
        "p": 90.17
      },
      {
        "t": 1777295175428,
        "p": 90.17
      },
      {
        "t": 1777303065676,
        "p": 92.53
      },
      {
        "t": 1777309127199,
        "p": 91.55
      },
      {
        "t": 1777313539684,
        "p": 91.66
      },
      {
        "t": 1777319416160,
        "p": 90.72
      },
      {
        "t": 1777323662522,
        "p": 90.45
      }
    ],
    "PYPL": [
      {
        "t": 1777239428856,
        "p": 50.48
      },
      {
        "t": 1777241229247,
        "p": 50.48
      },
      {
        "t": 1777244267196,
        "p": 50.48
      },
      {
        "t": 1777247313680,
        "p": 50.48
      },
      {
        "t": 1777252629545,
        "p": 50.48
      },
      {
        "t": 1777265022494,
        "p": 50.48
      },
      {
        "t": 1777274845065,
        "p": 50.48
      },
      {
        "t": 1777282755290,
        "p": 50.48
      },
      {
        "t": 1777289228841,
        "p": 50.48
      },
      {
        "t": 1777295175428,
        "p": 50.48
      },
      {
        "t": 1777303065676,
        "p": 50.03
      },
      {
        "t": 1777309127199,
        "p": 49.86
      },
      {
        "t": 1777313539684,
        "p": 49.77
      },
      {
        "t": 1777319416160,
        "p": 49.83
      },
      {
        "t": 1777323662522,
        "p": 49.77
      }
    ],
    "PLTR": [
      {
        "t": 1777239428856,
        "p": 143.09
      },
      {
        "t": 1777241229247,
        "p": 143.09
      },
      {
        "t": 1777244267196,
        "p": 143.09
      },
      {
        "t": 1777247313680,
        "p": 143.09
      },
      {
        "t": 1777252629545,
        "p": 143.09
      },
      {
        "t": 1777265022494,
        "p": 143.09
      },
      {
        "t": 1777274845065,
        "p": 143.09
      },
      {
        "t": 1777282755290,
        "p": 143.09
      },
      {
        "t": 1777289228841,
        "p": 143.09
      },
      {
        "t": 1777295175428,
        "p": 143.09
      },
      {
        "t": 1777303065676,
        "p": 144.12
      },
      {
        "t": 1777309127199,
        "p": 143.25
      },
      {
        "t": 1777313539684,
        "p": 143.47
      },
      {
        "t": 1777319416160,
        "p": 143.21
      },
      {
        "t": 1777323662522,
        "p": 143.1
      }
    ],
    "TSM": [
      {
        "t": 1777239428856,
        "p": 402.46
      },
      {
        "t": 1777241229247,
        "p": 402.46
      },
      {
        "t": 1777244267196,
        "p": 402.46
      },
      {
        "t": 1777247313680,
        "p": 402.46
      },
      {
        "t": 1777252629545,
        "p": 402.46
      },
      {
        "t": 1777265022494,
        "p": 402.46
      },
      {
        "t": 1777274845065,
        "p": 402.46
      },
      {
        "t": 1777282755290,
        "p": 402.46
      },
      {
        "t": 1777289228841,
        "p": 402.46
      },
      {
        "t": 1777295175428,
        "p": 402.46
      },
      {
        "t": 1777303065676,
        "p": 403.21
      },
      {
        "t": 1777309127199,
        "p": 401.9
      },
      {
        "t": 1777313539684,
        "p": 403.53
      },
      {
        "t": 1777319416160,
        "p": 404.63
      },
      {
        "t": 1777323662522,
        "p": 404.98
      }
    ],
    "GLD": [
      {
        "t": 1777239428856,
        "p": 433.25
      },
      {
        "t": 1777241229247,
        "p": 433.25
      },
      {
        "t": 1777244267196,
        "p": 433.25
      },
      {
        "t": 1777247313680,
        "p": 433.25
      },
      {
        "t": 1777252629545,
        "p": 433.25
      },
      {
        "t": 1777265022494,
        "p": 433.25
      },
      {
        "t": 1777274845065,
        "p": 433.25
      },
      {
        "t": 1777282755290,
        "p": 433.25
      },
      {
        "t": 1777289228841,
        "p": 433.25
      },
      {
        "t": 1777295175428,
        "p": 433.25
      },
      {
        "t": 1777303065676,
        "p": 429.45
      },
      {
        "t": 1777309127199,
        "p": 429.42
      },
      {
        "t": 1777313539684,
        "p": 429.94
      },
      {
        "t": 1777319416160,
        "p": 429.89
      },
      {
        "t": 1777323662522,
        "p": 429.89
      }
    ]
  }
}
