{
  "timestamp": 1777539788956,
  "meta": {
    "stocksTimestamp": 1777539760746,
    "newsTimestamp": 1777533046139,
    "sentimentTimestamp": 1777533046139,
    "tickersWithSentiment": 0,
    "tickersWithStddev": 17,
    "fallbackStddevPct": 1.5
  },
  "predictions": [
    {
      "ticker": "AMD",
      "name": "Advanced Micro Devices",
      "price": 337.11,
      "base": 4.3006,
      "momentum": 2.4997611001555247,
      "stddev": 0.6640574489503897,
      "usedFallbackStddev": false,
      "zBase": 6.476246907248064,
      "zMom": 3.7643747602058397,
      "sentimentScore": null,
      "sentimentBuzz": null,
      "newsCount": 0,
      "newsSignal": 0,
      "score": 13.789953026799786
    },
    {
      "ticker": "PYPL",
      "name": "",
      "price": 50.94,
      "base": 2.6189,
      "momentum": 1.676646706586819,
      "stddev": 0.5942544173824555,
      "usedFallbackStddev": false,
      "zBase": 4.407034972555374,
      "zMom": 2.821429100976708,
      "sentimentScore": null,
      "sentimentBuzz": null,
      "newsCount": 1,
      "newsSignal": 0.34657359027997264,
      "score": 8.345220142900303
    },
    {
      "ticker": "INTC",
      "name": "Intel Corp.",
      "price": 94.75,
      "base": 12.1036,
      "momentum": 5.584475540060823,
      "stddev": 2.843846676119352,
      "usedFallbackStddev": false,
      "zBase": 4.256066299789514,
      "zMom": 1.9637048603763934,
      "sentimentScore": null,
      "sentimentBuzz": null,
      "newsCount": 3,
      "newsSignal": 0.6931471805599453,
      "score": 7.179252031819733
    },
    {
      "ticker": "HIMX",
      "name": "",
      "price": 11.45,
      "base": 4.6618,
      "momentum": 2.7959471591637968,
      "stddev": 1.225902858913349,
      "usedFallbackStddev": false,
      "zBase": 3.80274828964202,
      "zMom": 2.2807248868333247,
      "sentimentScore": null,
      "sentimentBuzz": null,
      "newsCount": 0,
      "newsSignal": 0,
      "score": 6.404655088406845
    },
    {
      "ticker": "AMZN",
      "name": "Amazon.com Inc.",
      "price": 263.04,
      "base": 1.2861,
      "momentum": 0.5993520223350407,
      "stddev": 0.5087403647526626,
      "usedFallbackStddev": false,
      "zBase": 2.528008566069396,
      "zMom": 1.178109825483243,
      "sentimentScore": null,
      "sentimentBuzz": null,
      "newsCount": 10,
      "newsSignal": 1.1989476363991853,
      "score": 4.1408586670865555
    },
    {
      "ticker": "TSM",
      "name": "",
      "price": 393.83,
      "base": 0.3798,
      "momentum": 0.3202317313255654,
      "stddev": 0.11160882349163884,
      "usedFallbackStddev": false,
      "zBase": 1.0851428571428572,
      "zMom": 0.9149478037873299,
      "sentimentScore": null,
      "sentimentBuzz": null,
      "newsCount": 1,
      "newsSignal": 0.34657359027997264,
      "score": 1.5909417334923506
    },
    {
      "ticker": "GOOGL",
      "name": "Alphabet Inc. (Class A)",
      "price": 349.94,
      "base": 0.0457,
      "momentum": 0.05800274491864039,
      "stddev": 0.35006166902657937,
      "usedFallbackStddev": false,
      "zBase": 0.1305484263017957,
      "zMom": 0.16569293370487923,
      "sentimentScore": null,
      "sentimentBuzz": null,
      "newsCount": 14,
      "newsSignal": 1.354025100551105,
      "score": 0.9494527721558086
    },
    {
      "ticker": "NFLX",
      "name": "Netflix Inc.",
      "price": 92.12,
      "base": -0.1626,
      "momentum": -0.15329111376059293,
      "stddev": 0.13811276202390377,
      "usedFallbackStddev": false,
      "zBase": -0.4645714285714286,
      "zMom": -0.43797461074455124,
      "sentimentScore": null,
      "sentimentBuzz": null,
      "newsCount": 0,
      "newsSignal": 0,
      "score": -0.5256125757489121
    },
    {
      "ticker": "AAPL",
      "name": "Apple Inc.",
      "price": 270.17,
      "base": -0.1995,
      "momentum": -0.03964184910725655,
      "stddev": 0.32709817400787716,
      "usedFallbackStddev": false,
      "zBase": -0.5700000000000001,
      "zMom": -0.11326242602073301,
      "sentimentScore": null,
      "sentimentBuzz": null,
      "newsCount": 5,
      "newsSignal": -0.8958797346140275,
      "score": -1.1268957156179618
    },
    {
      "ticker": "META",
      "name": "Meta Platforms Inc.",
      "price": 669.12,
      "base": -0.3307,
      "momentum": -0.16625316520448075,
      "stddev": 0.25908083210423705,
      "usedFallbackStddev": false,
      "zBase": -0.944857142857143,
      "zMom": -0.47500904344137357,
      "sentimentScore": null,
      "sentimentBuzz": null,
      "newsCount": 14,
      "newsSignal": -1.354025100551105,
      "score": -1.8919169094730022
    },
    {
      "ticker": "NOW",
      "name": "",
      "price": 88.89,
      "base": -1.7682,
      "momentum": -0.3251850190625612,
      "stddev": 0.8601571566021254,
      "usedFallbackStddev": false,
      "zBase": -2.0556708578521996,
      "zMom": -0.37805302968952553,
      "sentimentScore": null,
      "sentimentBuzz": null,
      "newsCount": 2,
      "newsSignal": -0.5493061443340548,
      "score": -2.6184003232092796
    },
    {
      "ticker": "PLTR",
      "name": "",
      "price": 137.97,
      "base": -2.2737,
      "momentum": -0.616394657226954,
      "stddev": 0.9694354136900586,
      "usedFallbackStddev": false,
      "zBase": -2.345385745034204,
      "zMom": -0.635828492050553,
      "sentimentScore": null,
      "sentimentBuzz": null,
      "newsCount": 0,
      "newsSignal": 0,
      "score": -2.792764669496792
    },
    {
      "ticker": "TSLA",
      "name": "Tesla Inc.",
      "price": 372.8,
      "base": -0.8563,
      "momentum": -0.3528279696353941,
      "stddev": 0.2217862075526742,
      "usedFallbackStddev": false,
      "zBase": -2.4465714285714286,
      "zMom": -1.0080799132439833,
      "sentimentScore": null,
      "sentimentBuzz": null,
      "newsCount": 8,
      "newsSignal": -1.0986122886681098,
      "score": -3.845640655810143
    },
    {
      "ticker": "GLD",
      "name": "",
      "price": 417.41,
      "base": -1.0666,
      "momentum": -0.4096949783393623,
      "stddev": 0.32696623799525404,
      "usedFallbackStddev": false,
      "zBase": -3.0474285714285716,
      "zMom": -1.1705570809696066,
      "sentimentScore": null,
      "sentimentBuzz": null,
      "newsCount": 1,
      "newsSignal": -0.34657359027997264,
      "score": -4.325529453506998
    },
    {
      "ticker": "MSFT",
      "name": "Microsoft Corp.",
      "price": 424.46,
      "base": -1.1159,
      "momentum": -0.4012483281319746,
      "stddev": 0.34760825336629264,
      "usedFallbackStddev": false,
      "zBase": -3.188285714285714,
      "zMom": -1.1464237946627847,
      "sentimentScore": null,
      "sentimentBuzz": null,
      "newsCount": 21,
      "newsSignal": -1.545521226679158,
      "score": -5.212136432405381
    },
    {
      "ticker": "HIMS",
      "name": "",
      "price": 26.33,
      "base": -5.6611,
      "momentum": -2.527896768734487,
      "stddev": 1.4076831991042886,
      "usedFallbackStddev": false,
      "zBase": -4.021572470000472,
      "zMom": -1.7957852806249248,
      "sentimentScore": null,
      "sentimentBuzz": null,
      "newsCount": 0,
      "newsSignal": 0,
      "score": -6.188136663978454
    },
    {
      "ticker": "NVDA",
      "name": "NVIDIA Corp.",
      "price": 209.25,
      "base": -1.8389,
      "momentum": -0.8092368118101163,
      "stddev": 0.4111880955424807,
      "usedFallbackStddev": false,
      "zBase": -4.472162545401365,
      "zMom": -1.9680453315227662,
      "sentimentScore": null,
      "sentimentBuzz": null,
      "newsCount": 17,
      "newsSignal": -1.4451858789480823,
      "score": -7.979699658556652
    }
  ],
  "risers": [
    {
      "ticker": "AMD",
      "name": "Advanced Micro Devices",
      "price": 337.11,
      "base": 4.3006,
      "momentum": 2.4997611001555247,
      "stddev": 0.6640574489503897,
      "usedFallbackStddev": false,
      "zBase": 6.476246907248064,
      "zMom": 3.7643747602058397,
      "sentimentScore": null,
      "sentimentBuzz": null,
      "newsCount": 0,
      "newsSignal": 0,
      "score": 13.789953026799786
    },
    {
      "ticker": "PYPL",
      "name": "",
      "price": 50.94,
      "base": 2.6189,
      "momentum": 1.676646706586819,
      "stddev": 0.5942544173824555,
      "usedFallbackStddev": false,
      "zBase": 4.407034972555374,
      "zMom": 2.821429100976708,
      "sentimentScore": null,
      "sentimentBuzz": null,
      "newsCount": 1,
      "newsSignal": 0.34657359027997264,
      "score": 8.345220142900303
    },
    {
      "ticker": "INTC",
      "name": "Intel Corp.",
      "price": 94.75,
      "base": 12.1036,
      "momentum": 5.584475540060823,
      "stddev": 2.843846676119352,
      "usedFallbackStddev": false,
      "zBase": 4.256066299789514,
      "zMom": 1.9637048603763934,
      "sentimentScore": null,
      "sentimentBuzz": null,
      "newsCount": 3,
      "newsSignal": 0.6931471805599453,
      "score": 7.179252031819733
    },
    {
      "ticker": "HIMX",
      "name": "",
      "price": 11.45,
      "base": 4.6618,
      "momentum": 2.7959471591637968,
      "stddev": 1.225902858913349,
      "usedFallbackStddev": false,
      "zBase": 3.80274828964202,
      "zMom": 2.2807248868333247,
      "sentimentScore": null,
      "sentimentBuzz": null,
      "newsCount": 0,
      "newsSignal": 0,
      "score": 6.404655088406845
    },
    {
      "ticker": "AMZN",
      "name": "Amazon.com Inc.",
      "price": 263.04,
      "base": 1.2861,
      "momentum": 0.5993520223350407,
      "stddev": 0.5087403647526626,
      "usedFallbackStddev": false,
      "zBase": 2.528008566069396,
      "zMom": 1.178109825483243,
      "sentimentScore": null,
      "sentimentBuzz": null,
      "newsCount": 10,
      "newsSignal": 1.1989476363991853,
      "score": 4.1408586670865555
    }
  ],
  "fallers": [
    {
      "ticker": "NVDA",
      "name": "NVIDIA Corp.",
      "price": 209.25,
      "base": -1.8389,
      "momentum": -0.8092368118101163,
      "stddev": 0.4111880955424807,
      "usedFallbackStddev": false,
      "zBase": -4.472162545401365,
      "zMom": -1.9680453315227662,
      "sentimentScore": null,
      "sentimentBuzz": null,
      "newsCount": 17,
      "newsSignal": -1.4451858789480823,
      "score": -7.979699658556652
    },
    {
      "ticker": "HIMS",
      "name": "",
      "price": 26.33,
      "base": -5.6611,
      "momentum": -2.527896768734487,
      "stddev": 1.4076831991042886,
      "usedFallbackStddev": false,
      "zBase": -4.021572470000472,
      "zMom": -1.7957852806249248,
      "sentimentScore": null,
      "sentimentBuzz": null,
      "newsCount": 0,
      "newsSignal": 0,
      "score": -6.188136663978454
    },
    {
      "ticker": "MSFT",
      "name": "Microsoft Corp.",
      "price": 424.46,
      "base": -1.1159,
      "momentum": -0.4012483281319746,
      "stddev": 0.34760825336629264,
      "usedFallbackStddev": false,
      "zBase": -3.188285714285714,
      "zMom": -1.1464237946627847,
      "sentimentScore": null,
      "sentimentBuzz": null,
      "newsCount": 21,
      "newsSignal": -1.545521226679158,
      "score": -5.212136432405381
    },
    {
      "ticker": "GLD",
      "name": "",
      "price": 417.41,
      "base": -1.0666,
      "momentum": -0.4096949783393623,
      "stddev": 0.32696623799525404,
      "usedFallbackStddev": false,
      "zBase": -3.0474285714285716,
      "zMom": -1.1705570809696066,
      "sentimentScore": null,
      "sentimentBuzz": null,
      "newsCount": 1,
      "newsSignal": -0.34657359027997264,
      "score": -4.325529453506998
    },
    {
      "ticker": "TSLA",
      "name": "Tesla Inc.",
      "price": 372.8,
      "base": -0.8563,
      "momentum": -0.3528279696353941,
      "stddev": 0.2217862075526742,
      "usedFallbackStddev": false,
      "zBase": -2.4465714285714286,
      "zMom": -1.0080799132439833,
      "sentimentScore": null,
      "sentimentBuzz": null,
      "newsCount": 8,
      "newsSignal": -1.0986122886681098,
      "score": -3.845640655810143
    }
  ]
}
