{
  "timestamp": 1777862828557,
  "meta": {
    "stocksTimestamp": 1777862803380,
    "newsTimestamp": 1777852586782,
    "sentimentTimestamp": 1777852586782,
    "tickersWithSentiment": 0,
    "tickersWithStddev": 17,
    "fallbackStddevPct": 1.5
  },
  "predictions": [
    {
      "ticker": "INTC",
      "name": "Intel Corp.",
      "price": 99.62,
      "base": 5.4403,
      "momentum": 0.002007508080215344,
      "stddev": 0.006691425036509673,
      "usedFallbackStddev": false,
      "zBase": 15.543714285714286,
      "zMom": 0.005735737372043841,
      "sentimentScore": null,
      "sentimentBuzz": null,
      "newsCount": 2,
      "newsSignal": 0.5493061443340548,
      "score": 15.900044371193403
    },
    {
      "ticker": "HIMX",
      "name": "",
      "price": 12.31,
      "base": 4.766,
      "momentum": 0.00812149760418256,
      "stddev": 0.02706726860438311,
      "usedFallbackStddev": false,
      "zBase": 13.617142857142857,
      "zMom": 0.02320427886909303,
      "sentimentScore": null,
      "sentimentBuzz": null,
      "newsCount": 0,
      "newsSignal": 0,
      "score": 13.711935651220085
    },
    {
      "ticker": "PLTR",
      "name": "",
      "price": 144.07,
      "base": 3.5655,
      "momentum": 0.0013881562508742263,
      "stddev": 0.004627059073536653,
      "usedFallbackStddev": false,
      "zBase": 10.187142857142858,
      "zMom": 0.003966160716783504,
      "sentimentScore": null,
      "sentimentBuzz": null,
      "newsCount": 2,
      "newsSignal": 0.5493061443340548,
      "score": 10.52884769748817
    },
    {
      "ticker": "AAPL",
      "name": "Apple Inc.",
      "price": 280.14,
      "base": 3.2394,
      "momentum": 0.00071391345943415,
      "stddev": 0.0023796775580845722,
      "usedFallbackStddev": false,
      "zBase": 9.255428571428572,
      "zMom": 0.0020397527412404286,
      "sentimentScore": null,
      "sentimentBuzz": null,
      "newsCount": 8,
      "newsSignal": 1.0986122886681098,
      "score": 9.920259580369416
    },
    {
      "ticker": "NOW",
      "name": "",
      "price": 91.16,
      "base": 3.2273,
      "momentum": 0.002193800320258558,
      "stddev": 0.007312347025070932,
      "usedFallbackStddev": false,
      "zBase": 9.220857142857144,
      "zMom": 0.006268000915024452,
      "sentimentScore": null,
      "sentimentBuzz": null,
      "newsCount": 8,
      "newsSignal": 1.0986122886681098,
      "score": 9.897363418360632
    },
    {
      "ticker": "TSLA",
      "name": "Tesla Inc.",
      "price": 390.82,
      "base": 2.4081,
      "momentum": 0.0005117366807759846,
      "stddev": 0.0017057714794098764,
      "usedFallbackStddev": false,
      "zBase": 6.880285714285715,
      "zMom": 0.0014621048022170988,
      "sentimentScore": null,
      "sentimentBuzz": null,
      "newsCount": 1,
      "newsSignal": 0.34657359027997264,
      "score": 7.091247778088743
    },
    {
      "ticker": "MSFT",
      "name": "Microsoft Corp.",
      "price": 414.44,
      "base": 1.6332,
      "momentum": 0.0004825719152682632,
      "stddev": 0.001608557527392474,
      "usedFallbackStddev": false,
      "zBase": 4.666285714285714,
      "zMom": 0.0013787769007664664,
      "sentimentScore": null,
      "sentimentBuzz": null,
      "newsCount": 11,
      "newsSignal": 1.2424533248940002,
      "score": 5.413687839308685
    },
    {
      "ticker": "AMD",
      "name": "Advanced Micro Devices",
      "price": 360.54,
      "base": 1.7067,
      "momentum": 0.0005547142389624486,
      "stddev": 0.0018490269516247995,
      "usedFallbackStddev": false,
      "zBase": 4.876285714285715,
      "zMom": 0.001584897825606996,
      "sentimentScore": null,
      "sentimentBuzz": null,
      "newsCount": 4,
      "newsSignal": 0.8047189562170501,
      "score": 5.3614356124036275
    },
    {
      "ticker": "AMZN",
      "name": "Amazon.com Inc.",
      "price": 268.26,
      "base": 1.2073,
      "momentum": 0.0007455286916964481,
      "stddev": 0.002485058590251603,
      "usedFallbackStddev": false,
      "zBase": 3.4494285714285717,
      "zMom": 0.0021300819762755663,
      "sentimentScore": null,
      "sentimentBuzz": null,
      "newsCount": 7,
      "newsSignal": 1.0397207708399179,
      "score": 4.0754653036210575
    },
    {
      "ticker": "HIMS",
      "name": "",
      "price": 27.41,
      "base": 0.8833,
      "momentum": 0.003647904278970257,
      "stddev": 0.012158794433025782,
      "usedFallbackStddev": false,
      "zBase": 2.523714285714286,
      "zMom": 0.010422583654200734,
      "sentimentScore": null,
      "sentimentBuzz": null,
      "newsCount": 1,
      "newsSignal": 0.34657359027997264,
      "score": 2.7395495268609174
    },
    {
      "ticker": "PYPL",
      "name": "",
      "price": 50.44,
      "base": 0.5983,
      "momentum": 0.003964635451789141,
      "stddev": 0.013214404451492455,
      "usedFallbackStddev": false,
      "zBase": 1.7094285714285717,
      "zMom": 0.011327529862254689,
      "sentimentScore": null,
      "sentimentBuzz": null,
      "newsCount": 1,
      "newsSignal": 0.34657359027997264,
      "score": 1.9231818065536301
    },
    {
      "ticker": "GOOGL",
      "name": "Alphabet Inc. (Class A)",
      "price": 385.69,
      "base": 0.2313,
      "momentum": 0.0005185431012903184,
      "stddev": 0.0017284590804114018,
      "usedFallbackStddev": false,
      "zBase": 0.6608571428571429,
      "zMom": 0.0014815517179723383,
      "sentimentScore": null,
      "sentimentBuzz": null,
      "newsCount": 8,
      "newsSignal": 1.0986122886681098,
      "score": 1.320318244268609
    },
    {
      "ticker": "TSM",
      "name": "",
      "price": 397.67,
      "base": 0.4065,
      "momentum": 0.0005029219766726446,
      "stddev": 0.001676389728616444,
      "usedFallbackStddev": false,
      "zBase": 1.1614285714285715,
      "zMom": 0.0014369199333504133,
      "sentimentScore": null,
      "sentimentBuzz": null,
      "newsCount": 0,
      "newsSignal": 0,
      "score": 1.1619292353882058
    },
    {
      "ticker": "GLD",
      "name": "",
      "price": 423.18,
      "base": -0.1133,
      "momentum": 0.000472605426444331,
      "stddev": 0.0015753365325382152,
      "usedFallbackStddev": false,
      "zBase": -0.32371428571428573,
      "zMom": 0.0013503012184123743,
      "sentimentScore": null,
      "sentimentBuzz": null,
      "newsCount": 0,
      "newsSignal": 0,
      "score": -0.32376673912961584
    },
    {
      "ticker": "META",
      "name": "Meta Platforms Inc.",
      "price": 608.745,
      "base": -0.5172,
      "momentum": 0.00041067593146861957,
      "stddev": 0.001368908528997376,
      "usedFallbackStddev": false,
      "zBase": -1.4777142857142858,
      "zMom": 0.001173359804196056,
      "sentimentScore": null,
      "sentimentBuzz": null,
      "newsCount": 2,
      "newsSignal": -0.5493061443340548,
      "score": -1.8075060391801119
    },
    {
      "ticker": "NVDA",
      "name": "NVIDIA Corp.",
      "price": 198.45,
      "base": -0.5612,
      "momentum": 0.0010077800620840638,
      "stddev": 0.0033591991792646936,
      "usedFallbackStddev": false,
      "zBase": -1.6034285714285716,
      "zMom": 0.0028793716059544684,
      "sentimentScore": null,
      "sentimentBuzz": null,
      "newsCount": 37,
      "newsSignal": -1.8187930798631928,
      "score": -2.695258443350577
    },
    {
      "ticker": "NFLX",
      "name": "Netflix Inc.",
      "price": 92.06,
      "base": -1.6558,
      "momentum": 0.0021723546151314454,
      "stddev": 0.0072408675795524935,
      "usedFallbackStddev": false,
      "zBase": -4.730857142857143,
      "zMom": 0.00620672747180413,
      "sentimentScore": null,
      "sentimentBuzz": null,
      "newsCount": 1,
      "newsSignal": -0.34657359027997264,
      "score": -4.9423248739443775
    }
  ],
  "risers": [
    {
      "ticker": "INTC",
      "name": "Intel Corp.",
      "price": 99.62,
      "base": 5.4403,
      "momentum": 0.002007508080215344,
      "stddev": 0.006691425036509673,
      "usedFallbackStddev": false,
      "zBase": 15.543714285714286,
      "zMom": 0.005735737372043841,
      "sentimentScore": null,
      "sentimentBuzz": null,
      "newsCount": 2,
      "newsSignal": 0.5493061443340548,
      "score": 15.900044371193403
    },
    {
      "ticker": "HIMX",
      "name": "",
      "price": 12.31,
      "base": 4.766,
      "momentum": 0.00812149760418256,
      "stddev": 0.02706726860438311,
      "usedFallbackStddev": false,
      "zBase": 13.617142857142857,
      "zMom": 0.02320427886909303,
      "sentimentScore": null,
      "sentimentBuzz": null,
      "newsCount": 0,
      "newsSignal": 0,
      "score": 13.711935651220085
    },
    {
      "ticker": "PLTR",
      "name": "",
      "price": 144.07,
      "base": 3.5655,
      "momentum": 0.0013881562508742263,
      "stddev": 0.004627059073536653,
      "usedFallbackStddev": false,
      "zBase": 10.187142857142858,
      "zMom": 0.003966160716783504,
      "sentimentScore": null,
      "sentimentBuzz": null,
      "newsCount": 2,
      "newsSignal": 0.5493061443340548,
      "score": 10.52884769748817
    },
    {
      "ticker": "AAPL",
      "name": "Apple Inc.",
      "price": 280.14,
      "base": 3.2394,
      "momentum": 0.00071391345943415,
      "stddev": 0.0023796775580845722,
      "usedFallbackStddev": false,
      "zBase": 9.255428571428572,
      "zMom": 0.0020397527412404286,
      "sentimentScore": null,
      "sentimentBuzz": null,
      "newsCount": 8,
      "newsSignal": 1.0986122886681098,
      "score": 9.920259580369416
    },
    {
      "ticker": "NOW",
      "name": "",
      "price": 91.16,
      "base": 3.2273,
      "momentum": 0.002193800320258558,
      "stddev": 0.007312347025070932,
      "usedFallbackStddev": false,
      "zBase": 9.220857142857144,
      "zMom": 0.006268000915024452,
      "sentimentScore": null,
      "sentimentBuzz": null,
      "newsCount": 8,
      "newsSignal": 1.0986122886681098,
      "score": 9.897363418360632
    }
  ],
  "fallers": [
    {
      "ticker": "NFLX",
      "name": "Netflix Inc.",
      "price": 92.06,
      "base": -1.6558,
      "momentum": 0.0021723546151314454,
      "stddev": 0.0072408675795524935,
      "usedFallbackStddev": false,
      "zBase": -4.730857142857143,
      "zMom": 0.00620672747180413,
      "sentimentScore": null,
      "sentimentBuzz": null,
      "newsCount": 1,
      "newsSignal": -0.34657359027997264,
      "score": -4.9423248739443775
    },
    {
      "ticker": "NVDA",
      "name": "NVIDIA Corp.",
      "price": 198.45,
      "base": -0.5612,
      "momentum": 0.0010077800620840638,
      "stddev": 0.0033591991792646936,
      "usedFallbackStddev": false,
      "zBase": -1.6034285714285716,
      "zMom": 0.0028793716059544684,
      "sentimentScore": null,
      "sentimentBuzz": null,
      "newsCount": 37,
      "newsSignal": -1.8187930798631928,
      "score": -2.695258443350577
    },
    {
      "ticker": "META",
      "name": "Meta Platforms Inc.",
      "price": 608.745,
      "base": -0.5172,
      "momentum": 0.00041067593146861957,
      "stddev": 0.001368908528997376,
      "usedFallbackStddev": false,
      "zBase": -1.4777142857142858,
      "zMom": 0.001173359804196056,
      "sentimentScore": null,
      "sentimentBuzz": null,
      "newsCount": 2,
      "newsSignal": -0.5493061443340548,
      "score": -1.8075060391801119
    },
    {
      "ticker": "GLD",
      "name": "",
      "price": 423.18,
      "base": -0.1133,
      "momentum": 0.000472605426444331,
      "stddev": 0.0015753365325382152,
      "usedFallbackStddev": false,
      "zBase": -0.32371428571428573,
      "zMom": 0.0013503012184123743,
      "sentimentScore": null,
      "sentimentBuzz": null,
      "newsCount": 0,
      "newsSignal": 0,
      "score": -0.32376673912961584
    }
  ]
}
